rythmnet_func/__init__.py
rythmnet_func/utils/__init__.py
rythmnet_func/utils/engine_vipl.py
rythmnet_func/utils/model_utils.py
rythmnet_func/utils/plot_scripts.py
rythmnet_func/utils/resnet.py
rythmnet_func/utils/rhythmnet.py
rythmnet_func/utils/rhythmnet_loss.py
rythmnet_func-0.0.1.dist-info/METADATA
rythmnet_func-0.0.1.dist-info/WHEEL
rythmnet_func-0.0.1.dist-info/top_level.txt
rythmnet_func-0.0.1.dist-info/RECORD
